[
  {
    "user_id": "5ab469bf370e465e2b445e35",
    "user_index": 0,
    "user_name": "Bennett",
    "user_img": "../images/headImg0.jpg",
    "user_sex": "女",
    "user_sign": "",
    "way_index": [2, 10, 14],
    "article_index": [7, 1]
  },
  {
    "user_id": "5ab469bf43227c059fda7b86",
    "user_index": 1,
    "user_name": "Vance",
    "user_img": "../images/headImg1.jpg",
    "user_sex": "女",
    "user_sign": "",
    "way_index": [14, 0],
    "article_index": [13, 1]
  },
  {
    "user_id": "5ab469bf4037dad0edd66a5f",
    "user_index": 2,
    "user_name": "Walters",
    "user_img": "../images/headImg2.jpg",
    "user_sex": "女",
    "user_sign": "",
    "way_index": [9],
    "article_index": [5, 17]
  },
  {
    "user_id": "5ab469bf71d327333b49a48b",
    "user_index": 3,
    "user_name": "Black",
    "user_img": "../images/headImg3.jpg",
    "user_sex": "女",
    "user_sign": "",
    "way_index": [6, 19, 1, 12, 3],
    "article_index": [2, 2]
  },
  {
    "user_id": "5ab469bfcde1b2b06722e538",
    "user_index": 4,
    "user_name": "Avila",
    "user_img": "../images/headImg4.jpg",
    "user_sex": "男",
    "user_sign": "",
    "way_index": [12, 2, 3, 18, 5, 7, 16, 15],
    "article_index": [19, 15]
  },
  {
    "user_id": "5ab469bfe399b5618f74f6bf",
    "user_index": 5,
    "user_name": "Glass",
    "user_img": "../images/headImg5.jpg",
    "user_sex": "男",
    "user_sign": "",
    "way_index": [2, 19, 11, 6, 7, 4, 12],
    "article_index": [9, 6]
  },
  {
    "user_id": "5ab469bf820aa2bce30324a1",
    "user_index": 6,
    "user_name": "Dunn",
    "user_img": "../images/headImg6.jpg",
    "user_sex": "女",
    "user_sign": "",
    "way_index": [1, 11, 14],
    "article_index": [14, 18]
  },
  {
    "user_id": "5ab469bfc862f12603e851a4",
    "user_index": 7,
    "user_name": "Murphy",
    "user_img": "../images/headImg7.jpg",
    "user_sex": "女",
    "user_sign": "",
    "way_index": [10, 13, 4, 17],
    "article_index": [11]
  },
  {
    "user_id": "5ab469bf1011ba1fe53eb065",
    "user_index": 8,
    "user_name": "Stephenson",
    "user_img": "../images/headImg8.jpg",
    "user_sex": "男",
    "user_sign": "",
    "way_index": [3, 13, 13, 0, 3, 10, 2, 3],
    "article_index": [11]
  },
  {
    "user_id": "5ab469c00beda9b2b69ceeb6",
    "user_index": 9,
    "user_name": "Donovan",
    "user_img": "../images/headImg9.jpg",
    "user_sex": "女",
    "user_sign": "",
    "way_index": [0, 12, 14, 7, 1, 2],
    "article_index": [19]
  },
  {
    "user_id": "5ab469c0026495158ff32f51",
    "user_index": 10,
    "user_name": "Blankenship",
    "user_img": "../images/headImg10.jpg",
    "user_sex": "女",
    "user_sign": "",
    "way_index": [6, 8, 13],
    "article_index": []
  },
  {
    "user_id": "5ab469c01c0df00cf73db7cd",
    "user_index": 11,
    "user_name": "Shepard",
    "user_img": "../images/headImg11.jpg",
    "user_sex": "女",
    "user_sign": "",
    "way_index": [3, 17, 13, 6, 4, 13, 17],
    "article_index": [16]
  },
  {
    "user_id": "5ab469c0aee44b6e436b680e",
    "user_index": 12,
    "user_name": "Allison",
    "user_img": "../images/headImg12.jpg",
    "user_sex": "男",
    "user_sign": "",
    "way_index": [8, 14, 9, 5],
    "article_index": [12, 20]
  },
  {
    "user_id": "5ab469c01030721903d806e6",
    "user_index": 13,
    "user_name": "Marsh",
    "user_img": "../images/headImg13.jpg",
    "user_sex": "女",
    "user_sign": "",
    "way_index": [],
    "article_index": [15]
  },
  {
    "user_id": "5ab469c02bba18414d92e4ac",
    "user_index": 14,
    "user_name": "Berg",
    "user_img": "../images/headImg14.jpg",
    "user_sex": "男",
    "user_sign": "",
    "way_index": [18],
    "article_index": [13, 0]
  },
  {
    "user_id": "5ab469c0f00e0d24e99ab409",
    "user_index": 15,
    "user_name": "Schroeder",
    "user_img": "../images/headImg15.jpg",
    "user_sex": "女",
    "user_sign": "",
    "way_index": [6],
    "article_index": [4, 19]
  },
  {
    "user_id": "5ab469c02aaecf13110f3403",
    "user_index": 16,
    "user_name": "Callahan",
    "user_img": "../images/headImg16.jpg",
    "user_sex": "女",
    "user_sign": "",
    "way_index": [17, 8, 1, 12, 10, 19, 9, 1],
    "article_index": []
  },
  {
    "user_id": "5ab469c034a4c6bd7c96b40e",
    "user_index": 17,
    "user_name": "Conley",
    "user_img": "../images/headImg17.jpg",
    "user_sex": "女",
    "user_sign": "",
    "way_index": [19, 7, 7, 11, 4, 8],
    "article_index": []
  },
  {
    "user_id": "5ab469c075e7571c4de5a92f",
    "user_index": 18,
    "user_name": "Mccarthy",
    "user_img": "../images/headImg18.jpg",
    "user_sex": "男",
    "user_sign": "",
    "way_index": [11],
    "article_index": [18, 11]
  },
  {
    "user_id": "5ab469c0361fdd219929be9e",
    "user_index": 19,
    "user_name": "Clemons",
    "user_img": "../images/headImg19.jpg",
    "user_sex": "男",
    "user_sign": "",
    "way_index": [10, 16, 20, 3],
    "article_index": [13]
  },
  {
    "user_id": "5ab469c00eb031d6412626dd",
    "user_index": 20,
    "user_name": "Fletcher",
    "user_img": "../images/headImg20.jpg",
    "user_sex": "女",
    "user_sign": "",
    "way_index": [9],
    "article_index": [20, 11]
  },
  {
    "user_id": "5ab469c0767cc8aaf9e9806b",
    "user_index": 21,
    "user_name": "Gardner",
    "user_img": "../images/headImg21.jpg",
    "user_sex": "女",
    "user_sign": "",
    "way_index": [18, 2],
    "article_index": [20]
  },
  {
    "user_id": "5ab469c0e8152e59965950f8",
    "user_index": 22,
    "user_name": "Avery",
    "user_img": "../images/headImg22.jpg",
    "user_sex": "男",
    "user_sign": "",
    "way_index": [10],
    "article_index": [5]
  },
  {
    "user_id": "5ab469c04cb370fa68858690",
    "user_index": 23,
    "user_name": "Dunlap",
    "user_img": "../images/headImg23.jpg",
    "user_sex": "男",
    "user_sign": "",
    "way_index": [19, 7],
    "article_index": [5]
  },
  {
    "user_id": "5ab469c05e8d37d7e0aeee40",
    "user_index": 24,
    "user_name": "Pena",
    "user_img": "../images/headImg24.jpg",
    "user_sex": "男",
    "user_sign": "",
    "way_index": [16, 2, 12, 8, 11, 5, 19],
    "article_index": [2]
  },
  {
    "user_id": "5ab469c0c091910ddc93fa55",
    "user_index": 25,
    "user_name": "Hinton",
    "user_img": "../images/headImg25.jpg",
    "user_sex": "男",
    "user_sign": "",
    "way_index": [19, 9, 15, 10, 15, 2],
    "article_index": [12]
  },
  {
    "user_id": "5ab469c027cda0fdd0d36b13",
    "user_index": 26,
    "user_name": "Harrell",
    "user_img": "../images/headImg26.jpg",
    "user_sex": "男",
    "user_sign": "",
    "way_index": [4, 18, 8, 1],
    "article_index": [3]
  },
  {
    "user_id": "5ab469c1e5e2dce79092db94",
    "user_index": 27,
    "user_name": "Shannon",
    "user_img": "../images/headImg27.jpg",
    "user_sex": "女",
    "user_sign": "",
    "way_index": [],
    "article_index": [15, 13]
  },
  {
    "user_id": "5ab469c142b49dfe8f4e22bf",
    "user_index": 28,
    "user_name": "Becker",
    "user_img": "../images/headImg28.jpg",
    "user_sex": "男",
    "user_sign": "",
    "way_index": [18, 6, 13, 17, 0, 0, 7, 8],
    "article_index": []
  },
  {
    "user_id": "5ab469c184883949ff3a4c12",
    "user_index": 29,
    "user_name": "Bolton",
    "user_img": "../images/headImg29.jpg",
    "user_sex": "女",
    "user_sign": "",
    "way_index": [8, 5, 18, 10],
    "article_index": [5, 9]
  }
]
